mrl/__init__.py
mrl/aug.py
mrl/mrl.py
mrl/stl10_eval.py
mrl/utils.py
mrl/custom_datasets/__init__.py
mrl/custom_datasets/custom_datasets.py
mrl/custom_datasets/huggingface_dataset.py
mrl/encoders/__init__.py
mrl/encoders/models.py
mrl_pytorch-0.1.1.dist-info/LICENSE
mrl_pytorch-0.1.1.dist-info/METADATA
mrl_pytorch-0.1.1.dist-info/WHEEL
mrl_pytorch-0.1.1.dist-info/entry_points.txt
mrl_pytorch-0.1.1.dist-info/top_level.txt
mrl_pytorch-0.1.1.dist-info/RECORD
