Metadata-Version: 2.1
Name: mrl-pytorch
Version: 0.1.1
Summary: An unofficial implementation of Matryoshka Representation Learning for contrastive self-supervised learning
Home-page: https://github.com/filipbasara0/matryoshka-representation-learning
Author: Filip Basara
Author-email: basarafilip@gmail.com
License: MIT
Keywords: machine learning,pytorch,self-supervised learning,representation learning,contrastive learning
Platform: UNKNOWN
Classifier: Development Status :: 4 - Beta
Classifier: Intended Audience :: Developers
Classifier: Topic :: Scientific/Engineering :: Artificial Intelligence
Classifier: License :: OSI Approved :: MIT License
Classifier: Programming Language :: Python :: 3.10
Requires-Dist: datasets (>=2.15)
Requires-Dist: torch (>=2.1)
Requires-Dist: torchinfo (>=1.8.0)
Requires-Dist: torchvision (>=0.16)
Requires-Dist: tqdm (>=4.66)
